dbpedia_tag/__init__.py
dbpedia_tag/bp/__init__.py
dbpedia_tag/bp/tagger.py
dbpedia_tag/dmo/__init__.py
dbpedia_tag/dmo/candidate_fuzzy_match.py
dbpedia_tag/dmo/sliding_window_blacklist.py
dbpedia_tag/dmo/sliding_window_extract.py
dbpedia_tag/dmo/sliding_window_match.py
dbpedia_tag/dto/__init__.py
dbpedia_tag/dto/stopwords_kb.py
dbpedia_tag/recipes/__init__.py
dbpedia_tag/recipes/filter_entity_list.py
dbpedia_tag/svc/__init__.py
dbpedia_tag/svc/find_exact_matches.py
dbpedia_tag/svc/find_fuzzy_matches.py
dbpedia_tag/svc/perform_text_replacement.py
dbpedia_tag-0.1.13.dist-info/WHEEL
dbpedia_tag-0.1.13.dist-info/METADATA
dbpedia_tag-0.1.13.dist-info/RECORD
