Metadata-Version: 2.1
Name: dbpedia-tag
Version: 0.1.13
Summary: Perform runtime tagging and annotation of unstructured text
Author: Craig Trim
Author-email: craigtrim@gmail.com
Requires-Python: ==3.8.5
Classifier: Programming Language :: Python :: 3
Requires-Dist: baseblock
Requires-Dist: dbpedia-ent
Requires-Dist: fast-sentence-tokenize
